{"place_info":{"d_activity_gwj_section":"0-+","d_brand_filter_section":"0-+","d_brand_id_section":"0-+","d_business_id":"","d_business_type":"scope","d_capsule_filter_section":"0-+","d_cater_book_pc_section":"0-+","d_cater_book_wap_section":"0-+","d_cater_rating_section":"0-+","d_data_type":"scope","d_discount2_section":"0-+","d_discount_section":"0-+","d_discount_tm2_section":"0-+","d_discount_tm_section":"0-+","d_dist":"0-+","d_filt_type_section":"0-+","d_free_section":"0-+","d_groupon_section":"0-+","d_groupon_type_section":"0-+","d_health_score_section":"0-+","d_hesuan_time_section":"0-+","d_hotel_attr_tags_section":"0-+","d_hotel_book_pc_section":"0-+","d_hotel_book_wap_section":"0-+","d_hotel_detail_tag_section":"0-+","d_hourly_day1_bookable_section":"0-+","d_hourly_day1_fullroom_section":"0-+","d_hourly_day1_price_section":"0-+","d_hourly_day2_bookable_section":"0-+","d_hourly_day2_fullroom_section":"0-+","d_hourly_day2_price_section":"0-+","d_hourly_day3_bookable_section":"0-+","d_hourly_day3_fullroom_section":"0-+","d_hourly_day3_price_section":"0-+","d_hourly_day4_bookable_section":"0-+","d_hourly_day4_fullroom_section":"0-+","d_hourly_day4_price_section":"0-+","d_hourly_day5_bookable_section":"0-+","d_hourly_day5_fullroom_section":"0-+","d_hourly_day5_price_section":"0-+","d_int_filter1_section":"0-+","d_int_filter2_section":"0-+","d_level_section":"0-+","d_lowprice_flag_section":"0-+","d_meishipaihao_section":"0-+","d_movie_book_section":"0-+","d_overall_rating_section":"0-+","d_parking_type_section":"0-+","d_price_section":"0-+","d_query_attr_type":"2","d_rebate_section":"0-+","d_room_section":"0-+","d_service_filter_section":"0-+","d_sort_rule":"0","d_sort_type":"","d_spothot_section":"0-+","d_sub_type":"","d_support_imax_section":"0-+","d_tab_filter_section":"0-+","d_tag_filter":"0","d_tag_info_list":"\u65c5\u6e38\u666f\u70b9","d_tag_section":"0-+","d_tags_beauty_section":"0-+","d_tags_cater_section":"0-+","d_tags_hospital_section":"0-+","d_tags_hotel_section":"0-+","d_tags_life_section":"0-+","d_tags_scope_section":"0-+","d_tags_shopping_section":"0-+","d_text_filter_section":"0-+","d_ticket_book_flag_section":"0-+","d_title_suffix_section":"0-+","d_tonight_sale_flag_section":"0-+","d_total_score_section":"0-+","d_wise_price_section":"0-+","search_ext":[{"title":"","wd":"\u6df1\u5733\u5e02\u9f99\u534e\u533a\u666f\u70b9"}]},"content":[{"acc_flag":0,"addr":"\u6df1\u5733\u5e02\u9f99\u534e\u533a\u89c2\u6f9c\u9547\u541b\u5b50\u5e03\u6751\u73af\u89c2\u5357\u8def\u89c2\u6f9c\u5c71\u6c34\u7530\u56ed\u519c\u5e84\u65c5\u6e38\u6587\u5316\u56ed\u5185","addr_hot_percent":0,"address_color_shows":[{"end":12,"name":"\u6df1\u5733\u5e02\u9f99\u534e\u533a","start":0}],"address_norm":"[\u5e7f\u4e1c\u7701(440000)|PROV|0|][\u6df1\u5733\u5e02(440300)|CITY|1|][\u9f99\u534e\u533a(440309)|AREA|1|]\u89c2\u6f9c\u9547\u541b\u5b50\u5e03\u6751\u73af\u89c2\u5357\u8def\u89c2\u6f9c\u5c71\u6c34\u7530\u56ed\u519c\u5e84\u65c5\u6e38\u6587\u5316\u56ed\u5185","admin_info":{"area_id":440309,"area_name":"\u9f99\u534e\u533a","city_id":440300,"city_name":"\u6df1\u5733\u5e02","province_id":440000,"province_name":"\u5e7f\u4e1c\u7701","town_id":440309006,"town_name":"\u89c2\u6f9c\u8857\u9053"},"alias":["\u89c2\u6f9c\u5c71\u6c34\u7530\u56ed\u65c5\u6e38\u6587\u5316\u56ed-\u8bb8\u613f\u6c60"],"api_admin_info":{"area_code":3352,"area_name":"\u9f99\u534e\u533a","city_code":340,"city_name":"\u6df1\u5733\u5e02","prov_code":7,"prov_name":"\u5e7f\u4e1c\u7701"},"area":3352,"area_name":"\u6df1\u5733\u5e02\u9f99\u534e\u533a","biz_type":0,"brand_id":null,"catalogID":154,"city_id":340,"city_name":"\u6df1\u5733\u5e02","cla":[[17,"\u65c5\u6e38<font color=\"#c60a00\">\u666f\u70b9<\/font>"],[154,"\u98ce\u666f\u533a\/\u65c5\u6e38\u533a"]],"class_similar_score":0.54612112045288,"click_flag":0,"detail":1,"diPointX":1270299339,"diPointY":258151433,"di_tag":"\u65c5\u6e38\u666f\u70b9 \u98ce\u666f\u533a","dis":-1,"dist2route":0,"dist2start":0,"ernie_score":0,"ext":{"detail_info":{"areaid":"3352","bubble_info":{"icon":{"dark_icon_url":null,"icon_url":null,"std_tag":"\u65c5\u6e38\u666f\u70b9;\u666f\u70b9"},"mark":null,"sub_title":null,"tag":null,"title":null},"comments":[],"content_sug":{"search_ext_data":{"full_text":[]},"sug_ext_data":{"full_text":[],"sub_link_info":[]}},"default_image":"https:\/\/map-mobile-resource.cdn.bcebos.com\/icon\/rec\/search\/default\/huanzijingdiantongyong.png","display_info_comment_label":{"hotel":"","life":""},"display_info_redu":"0","free":[],"from_pds":"1","guide":[],"image":"https:\/\/map-mobile-resource.cdn.bcebos.com\/icon\/rec\/search\/default\/huanzijingdiantongyong.png","is_default_image":"1","list_min_price":[],"list_min_price_save":[],"mbc":{"markv":"1"},"name":"\u8bb8\u613f\u6c60","navi_xy":{"bid":"1217235448975533907","diPoint":{"x":"12702989.840000","y":"2581510.200000"},"navi_info":[{"bid":"0","from":"","is_traffic":1,"name":"","navi_x":"12703092.255400","navi_y":"2581309.261000","uid":"2bfcb14cf5cb2cfcc23644f2"}],"navixy_src":"navi.navi_xy_jingzhun_aoi","update_time":1695730864},"parking":{"action_type":["openApi"],"card_name":"searchSugParking","image_more":{"dark_url":"https:\/\/map-mobile-opnimg.cdn.bcebos.com\/903f76474ddbc2a23aafb16129f957c3.png","default_url":"https:\/\/map-mobile-opnimg.cdn.bcebos.com\/2ec3a31215dba6308054395b5468247a.png"},"jump_more":{"action_type":"openApi","action_value":"baidumap:\/\/map\/place\/detail?uid=7c605ed0f27b9efbb6f42fb4&show_type=detail_page&poi_ext_param={\"anchor\":{\"tabName\": \"gailan\",\"cardName\": \"smartjourney\"}}","log_click_key":"PoiSearchPG.ParkingClickMore","log_click_params":{"stdtag":"lvyoujindian"}},"jump_poi_parking":{"action_type":"openApi","action_value":"baidumap:\/\/map\/place\/detail?uid=e42f694c48d4dcb5774ff152&ext_parkjson=[{\"uid\": \"f4751a7102ad3b224e776efd\", \"std_tag\": \"\\u4ea4\\u901a\\u8bbe\\u65bd;\\u505c\\u8f66\\u573a\", \"name\": \"\\u89c2\\u6f9c\\u5c71\\u6c34\\u7530\\u56ed\\u65c5\\u6e38\\u6587\\u5316\\u56ed-\\u505c\\u8f66\\u573a\", \"y\": 2581889.9, \"x\": 12703057.82, \"desc\": \"\"}]&show_type=detail_bar","authorized_tag":"84%\u7528\u6237\u9009\u62e9","desc":["\u5bf9\u5916\u5f00\u653e","\u666f\u533a\u5185"],"dis2door":121,"log_click_key":"PoiSearchPG.ParkingClick","log_click_params":{"stdtag":"lvyoujindian"},"name":"\u89c2\u6f9c\u5c71\u6c34\u7530\u56ed\u65c5\u6e38\u6587\u5316\u56ed-\u505c\u8f66\u573a","pv_score":84,"suid":"e42f694c48d4dcb5774ff152","x":12703066.81,"y":2581454.95},"log_show_key":"PoiSearchPG.ParkingShow","log_show_params":{"main_poi_uid":"7c605ed0f27b9efbb6f42fb4","recom_poi_uid":"e42f694c48d4dcb5774ff152","stdtag":"lvyoujindian"},"status":1,"std_tag":"","title":"\u6700\u4f73\u505c\u8f66\u63a8\u8350"},"phone":"","poi_address":"\u6df1\u5733\u5e02\u9f99\u534e\u533a\u89c2\u6f9c\u9547\u541b\u5b50\u5e03\u6751\u73af\u89c2\u5357\u8def\u89c2\u6f9c\u5c71\u6c34\u7530\u56ed\u519c\u5e84\u65c5\u6e38\u6587\u5316\u56ed\u5185","point":{"x":12702993.39,"y":2581514.33},"price":[],"relate":{"has_relate":"2"},"scope_bars":{"aitravel_url":"https:\/\/client.map.baidu.com\/h5-project\/global-tourism\/global-tourism.html?city_id=340","has_ar_bar":1,"has_feeaudio":0,"package_slogan_list":["\u8ddf\u7740\u5c0f\u5ea6\u53bb\u8d4f\u6e38"],"tgt_uid":"e2c734e4fb03474414a190ed"},"short_desc":"","std_tag":"\u65c5\u6e38\u666f\u70b9;\u666f\u70b9","street":{"finepic":"","finepic_id":"","indoor_pano":"","interstartpid":"","ismodified":0,"pano":0,"pano_level":99,"street_gif_route_bubble":"","street_id":"7c605ed0f27b9efbb6f42fb4"},"tag":[],"taxi_info":[],"travel_info":{"navi_parking_relation":{"rec_parking_pv":[{"bid":"5041219223021013771","pv":347,"rate":8},{"bid":"7673894458466954525","pv":92,"rate":2},{"bid":"3429038704417893587","pv":1802,"rate":46},{"bid":"5898613215655427319","pv":884,"rate":22},{"bid":"125869303682136616","pv":267,"rate":6},{"bid":"8277288561649111521","pv":519,"rate":13}],"transfer":1}},"vs_content":{"cjh_hotel_activity":{"hotel_detail":""},"invisible":{"bigdata":{"showtag":"[[\"\\u666f\\u70b9\"], [\"\"], \"\", 0, \"\"]"}}}},"src_name":"scope"},"ext_display":{"display_info":{"catalog_fields":null,"impression_tag":{"hotel":"","life":""},"redu":"0","source_map":[],"src_name":"display_info","uids":["1217235448975533907:redu"]}},"ext_type":4,"f_flag":2060,"father_son":0,"gbrank_score":-8.9199968205382,"geo":"1|12702993.39,2581514.33;12702993.39,2581514.33|12702993.39,2581514.33;","geo_type":0,"history_address":"\u6df1\u5733\u5e02","hit_tag_press":0,"indoor_pano":"","is_nearnest_nat":0,"is_top_nat":0,"ismodified":0,"name":"\u8bb8\u613f\u6c60","navi_update_time":1708294467,"navi_x":"12703092.2554","navi_y":"2581309.261","new_catalog_id":"0c0a00","pano":0,"parent_id":"1257890518205988863","poiType":0,"poi_click_num":0,"poi_profile":0,"primary_uid":"1217235448975533907","prio_flag":32,"profile_geo":"","qu_brandid":0,"query_guide":"[{\"icon\":\"https:\\\/\\\/map-mobile-resource.cdn.bcebos.com\\\/icon\\\/service\\\/search\\\/default\\\/meishi5.png\",\"text\":\"\u7f8e\u98df\",\"type\":1},{\"icon\":\"https:\\\/\\\/map-mobile-resource.cdn.bcebos.com\\\/icon\\\/rec\\\/search\\\/default\\\/jiudian.png\",\"text\":\"\u9152\u5e97\",\"type\":1},{\"icon\":\"https:\\\/\\\/map-mobile-resource.cdn.bcebos.com\\\/icon\\\/rec\\\/search\\\/default\\\/jingdian.png\",\"text\":\"\u666f\u70b9\",\"type\":1},{\"icon\":\"https:\\\/\\\/map-mobile-resource.cdn.bcebos.com\\\/icon\\\/rec\\\/search\\\/default\\\/tingchechang.png\",\"text\":\"\u505c\u8f66\u573a\",\"type\":1},{\"icon\":\"https:\\\/\\\/map-mobile-resource.cdn.bcebos.com\\\/icon\\\/rec\\\/search\\\/default\\\/xiuxianyule.png\",\"text\":\"\u4f11\u95f2\u5a31\u4e50\",\"type\":1},{\"icon\":\"https:\\\/\\\/map-mobile-resource.cdn.bcebos.com\\\/icon\\\/service\\\/search\\\/default\\\/gouwu5.png\",\"text\":\"\u8d2d\u7269\",\"type\":1},{\"icon\":\"https:\\\/\\\/map-mobile-resource.cdn.bcebos.com\\\/icon\\\/rec\\\/search\\\/default\\\/jiayou.png\",\"text\":\"\u52a0\u6cb9\u7ad9\",\"type\":1}]","route_flag":0,"show_tag":[],"status":1,"std_tag":"\u65c5\u6e38\u666f\u70b9;\u666f\u70b9","std_tag_id":"1511","storage_src":"api","street_id":"7c605ed0f27b9efbb6f42fb4","tag":"\u65c5\u6e38<font color=\"#c60a00\">\u666f\u70b9<\/font> \u98ce\u666f\u533a","title_color_shows":[],"top1_reinforce":0,"ty":0,"uid":"7c605ed0f27b9efbb6f42fb4","view_type":0,"x":1270299339,"y":258151433},{"acc_flag":0,"addr":"\u6df1\u5733\u5e02\u9f99\u534e\u533a\u7f8e\u6f9c\u8def\u5927\u548c\u540d\u5c45\u5357\u4fa7\u7ea630\u7c73","addr_hot_percent":0,"address_color_shows":[{"end":12,"name":"\u6df1\u5733\u5e02\u9f99\u534e\u533a","start":0}],"address_norm":"[\u5e7f\u4e1c\u7701(440000)|PROV|0|][\u6df1\u5733\u5e02(440300)|CITY|1|][\u9f99\u534e\u533a(440309)|AREA|1|][\u7f8e\u6f9c\u8def()|ROAD|1|]\u5927\u548c\u540d\u5c45\u5357\u4fa7\u7ea630\u7c73","admin_info":{"area_id":440309,"area_name":"\u9f99\u534e\u533a","city_id":440300,"city_name":"\u6df1\u5733\u5e02","province_id":440000,"province_name":"\u5e7f\u4e1c\u7701","town_id":440309005,"town_name":"\u89c2\u6e56\u8857\u9053"},"aoi":"\u89c2\u6f9c","api_admin_info":{"area_code":3352,"area_name":"\u9f99\u534e\u533a","city_code":340,"city_name":"\u6df1\u5733\u5e02","prov_code":7,"prov_name":"\u5e7f\u4e1c\u7701"},"area":3352,"area_name":"\u6df1\u5733\u5e02\u9f99\u534e\u533a","biz_type":0,"brand_id":null,"catalogID":0,"city_id":340,"city_name":"\u6df1\u5733\u5e02","cla":[],"class_similar_score":0.53955936431885,"click_flag":0,"detail":1,"diPointX":1269700911,"diPointY":257828345,"di_tag":"\u65c5\u6e38\u666f\u70b9","dis":-1,"dist2route":0,"dist2start":0,"ernie_score":0,"ext":{"detail_info":{"areaid":"3352","bubble_info":{"icon":{"dark_icon_url":null,"icon_url":null,"std_tag":"\u65c5\u6e38\u666f\u70b9"},"mark":null,"sub_title":null,"tag":null,"title":null},"content_sug":{"search_ext_data":{"full_text":[]},"sug_ext_data":{"full_text":[],"sub_link_info":[]}},"default_image":"https:\/\/map-mobile-resource.cdn.bcebos.com\/icon\/rec\/search\/default\/huanzijingdiantongyong.png","from_pds":"1","image":"https:\/\/map-mobile-resource.cdn.bcebos.com\/icon\/rec\/search\/default\/huanzijingdiantongyong.png","is_default_image":"1","mbc":{"markv":"1"},"name":"\u53e4\u56ed","phone":"","poi_address":"\u6df1\u5733\u5e02\u9f99\u534e\u533a\u7f8e\u6f9c\u8def\u5927\u548c\u540d\u5c45\u5357\u4fa7\u7ea630\u7c73","poi_tags":{"attr_tag":[{"from":"time_renqun_new","invisible":1,"name":"\u9002\u5408\u5e74\u8f7b\u4eba","rate":1,"rec_num":1,"rec_reason":"\u8fd9\u91cc\u6709\u5f88\u591a\u9002\u5408\u5e74\u8f7b\u4eba\u7684\u523a\u6fc0\u9879\u76ee\uff0c\u4f60\u503c\u5f97\u4e00\u8bd5","type":2}],"transfer_update":1},"point":{"x":12697009.11,"y":2578283.45},"short_desc":"","std_tag":"\u65c5\u6e38\u666f\u70b9","tag":"\u65c5\u6e38\u666f\u70b9","travel_info":{"navi_parking_relation":{"rec_parking_pv":[{"bid":"11093999624693775908","pv":2,"rate":15},{"bid":"10014351216640932569","pv":11,"rate":84}],"rec_parkings":[{"distance":89,"is_children_parking":0,"is_confi_parking":0,"name":"\u5927\u548c\u96c5\u82d1-\u505c\u8f66\u573a","std_tag":"\u4ea4\u901a\u8bbe\u65bd;\u505c\u8f66\u573a","uid":"405268a469c2e4ccfe0eb060"},{"distance":354,"is_children_parking":0,"is_confi_parking":0,"name":"\u7fe0\u5e7d\u8def\u5317\u4fa7\u4e34\u65f6\u505c\u8f66\u70b9","std_tag":"\u4ea4\u901a\u8bbe\u65bd;\u505c\u8f66\u573a","uid":"e403a17c571084e6d1f49e25"}],"transfer":1,"update_time":1692963250.7177}},"vs_content":{"invisible":{"bigdata":{"dyn_style":"{\"dish\": [[\"\\u63a8\\u8350\\u83dc:{name}\", \"\"], [\"24\", \"24\"], \"310\", 2, \"\"]}","idx_type":"{\"1\": \"\\u83dc\\u54c1\", \"2\": \"\\u670d\\u52a1\\u5185\\u5bb9\", \"3\": \"\\u5546\\u54c1\", \"4\": \"\\u5b50\\u7c7b\\u578b\"}","showtag":"[[\"\\u65c5\\u6e38\\u666f\\u70b9\"], [\"\"], \"\", 0, \"\"]","style":"{\"24\": \"#F76454\", \"310\": \"#FEEFED\"}"}}}},"src_name":"scope"},"ext_display":null,"ext_type":4,"f_flag":2056,"father_son":0,"gbrank_score":-8.9312118947788,"geo":"1|12697009.11,2578283.45;12697009.11,2578283.45|12697009.11,2578283.45;","geo_type":0,"history_address":"\u6df1\u5733\u5e02","hit_tag_press":0,"is_nearnest_nat":0,"is_top_nat":0,"name":"\u53e4\u56ed","navi_update_time":1692963250,"navi_x":"0","navi_y":"0","new_catalog_id":"0c0000","poiType":0,"poi_click_num":0,"poi_profile":0,"primary_uid":"17565898315126128323","prio_flag":32,"qu_brandid":0,"query_guide":"[{\"icon\":\"https:\\\/\\\/map-mobile-resource.cdn.bcebos.com\\\/icon\\\/service\\\/search\\\/default\\\/meishi5.png\",\"text\":\"\u7f8e\u98df\",\"type\":1},{\"icon\":\"https:\\\/\\\/map-mobile-resource.cdn.bcebos.com\\\/icon\\\/rec\\\/search\\\/default\\\/jiudian.png\",\"text\":\"\u9152\u5e97\",\"type\":1},{\"icon\":\"https:\\\/\\\/map-mobile-resource.cdn.bcebos.com\\\/icon\\\/rec\\\/search\\\/default\\\/jingdian.png\",\"text\":\"\u666f\u70b9\",\"type\":1},{\"icon\":\"https:\\\/\\\/map-mobile-resource.cdn.bcebos.com\\\/icon\\\/rec\\\/search\\\/default\\\/tingchechang.png\",\"text\":\"\u505c\u8f66\u573a\",\"type\":1},{\"icon\":\"https:\\\/\\\/map-mobile-resource.cdn.bcebos.com\\\/icon\\\/rec\\\/search\\\/default\\\/xiuxianyule.png\",\"text\":\"\u4f11\u95f2\u5a31\u4e50\",\"type\":1},{\"icon\":\"https:\\\/\\\/map-mobile-resource.cdn.bcebos.com\\\/icon\\\/service\\\/search\\\/default\\\/gouwu5.png\",\"text\":\"\u8d2d\u7269\",\"type\":1},{\"icon\":\"https:\\\/\\\/map-mobile-resource.cdn.bcebos.com\\\/icon\\\/rec\\\/search\\\/default\\\/jiayou.png\",\"text\":\"\u52a0\u6cb9\u7ad9\",\"type\":1}]","route_flag":0,"show_tag":[],"status":1,"std_tag":"\u65c5\u6e38\u666f\u70b9","std_tag_id":"1500","storage_src":"api","tag":"\u65c5\u6e38<font color=\"#c60a00\">\u666f\u70b9<\/font>","title_color_shows":[],"top1_reinforce":0,"ty":0,"uid":"36079ae1c680e32133621212","view_type":0,"x":1269700911,"y":257828345},{"acc_flag":0,"addr":"\u5e7f\u4e1c\u7701\u6df1\u5733\u5e02\u9f99\u534e\u533a\u9f99\u534e\u8857\u9053\u6c11\u79c0\u8def\u4e0e\u6e05\u79c0\u8def\u4ea4\u53c9\u53e3\u6b63\u4e1c\u65b9\u5411161\u7c73","addr_hot_percent":0,"address_color_shows":[{"end":22,"name":"\u6df1\u5733\u5e02\u9f99\u534e\u533a\u9f99\u534e","start":6}],"address_norm":"[\u5e7f\u4e1c\u7701(440000)|PROV|1|][\u6df1\u5733\u5e02(440300)|CITY|1|][\u9f99\u534e\u533a(440309)|AREA|1|][\u6e05\u79c0\u8def()|ROAD|0|]\u9f99\u534e\u8857\u9053\u6c11\u79c0\u8def\u4e0e\u6e05\u79c0\u8def\u4ea4\u53c9\u53e3\u6b63\u4e1c\u65b9\u5411161\u7c73","admin_info":{"area_id":440309,"area_name":"\u9f99\u534e\u533a","city_id":440300,"city_name":"\u6df1\u5733\u5e02","province_id":440000,"province_name":"\u5e7f\u4e1c\u7701","town_id":440309003,"town_name":"\u9f99\u534e\u8857\u9053"},"alias":["\u6df1\u8d85\u5149\u7535"],"aoi":"\u9f99\u534e","api_admin_info":{"area_code":3352,"area_name":"\u9f99\u534e\u533a","city_code":340,"city_name":"\u6df1\u5733\u5e02","prov_code":7,"prov_name":"\u5e7f\u4e1c\u7701"},"area":3352,"area_name":"\u6df1\u5733\u5e02\u9f99\u534e\u533a","biz_type":0,"brand_id":null,"catalogID":262,"city_id":340,"city_name":"\u6df1\u5733\u5e02","cla":[[26,"\u516c\u53f8\u4f01\u4e1a"]],"class_similar_score":0.73467046022415,"click_flag":0,"detail":1,"diPointX":1269657543,"diPointY":257480052,"di_tag":"\u516c\u53f8\u4f01\u4e1a \u65c5\u6e38\u666f\u70b9","dis":-1,"dist2route":0,"dist2start":0,"ernie_score":0,"ext":{"detail_info":{"areaid":"3352","bangdan":[],"bangdan_head":{"detail_head":{"name":"\u9644\u8fd1\u4f18\u8d28\u7f8e\u98df\u00b7\u666f\u70b9\u00b7\u9152\u5e97","rank_s":" ","url":"https:\/\/ugc.map.baidu.com\/cube\/feed\/bangdancollect?city_id=340&tab1=%E7%BE%8E%E9%A3%9F&tab2=%E5%9F%8E%E5%B8%82%E5%BF%85%E5%90%83&district_index=%E9%BE%99%E5%8D%8E%E5%8C%BA&shangquan_index=%E9%BE%99%E5%8D%8E&pass_back=085db09e4265a7242541a58068336cc8&ebmfrom=non_consumer_jh&uid=c4be2a16a63f3daf33621219"},"head_icon_bubble_info":{"arrow_url":"https:\/\/map-mobile-resource.cdn.bcebos.com\/icon\/service\/bottom-imag\/default\/waterbubble-arrow.png","buried_point":"{\"water_bubble\": {\"wbType\": \"bangdan_default_085db09e4265a7242541a58068336cc8\"}}","icon_url":"https:\/\/map-mobile-resource.cdn.bcebos.com\/icon\/service\/bottom-imag\/default\/waterbubble-bangdan.png","jump_url":"https:\/\/ugc.map.baidu.com\/cube\/feed\/newhotlistpage?pass_back=085db09e4265a7242541a58068336cc8&ebmfrom=water_bubble_nxf","new_color":"#F03E72","new_text":"\u9644\u8fd1\u7f8e\u98df\u6392\u884c","text":"<font color=\"#F03E72\">\u9644\u8fd1\u7f8e\u98df\u6392\u884c<\/font><font color=\"#F6303F\">\uff1e<\/font>"}},"bubble_info":{"icon":{"dark_icon_url":null,"icon_url":null,"std_tag":"\u516c\u53f8\u4f01\u4e1a;\u56ed\u533a"},"mark":null,"sub_title":null,"tag":null,"title":null},"comment_num":3,"comments":[{"cn_name":"\u767e\u5ea6\u5730\u56fe","comment_jump_url":"https:\/\/ugc.map.baidu.com\/cube\/comment\/choicepage?tab=1&uid=c4be2a16a63f3daf33621219&comment_sort=1","comment_photo":[{"live":0,"pic_name":null,"pic_url":"https:\/\/lbsugc.cdn.bcebos.com\/images\/B64d76b51d03e41046b.jpeg"},{"live":0,"pic_name":null,"pic_url":"https:\/\/lbsugc.cdn.bcebos.com\/images\/B64d76b658f21efcdb.jpeg"}],"content":"","date":"2023-08-12 19:22","one_url_mobile":null,"overall_rating":0,"user_logo":"https:\/\/himg.bdimg.com\/sys\/portrait\/item\/ma.1.657eb94b.RXtgXTMvteHL0DEo2QBkkQ.jpg","user_name":"5bGx5LiK6Zu+5aSn"},{"cn_name":"\u767e\u5ea6\u5730\u56fe","comment_jump_url":"https:\/\/ugc.map.baidu.com\/cube\/comment\/choicepage?tab=1&uid=c4be2a16a63f3daf33621219&comment_sort=2","comment_photo":[],"content":"6auY56eR5oqA5bCx5piv56ys5LiA55Sf5Lqn5Yqb77yB","date":"2020-03-13 07:58","one_url_mobile":null,"overall_rating":0,"user_logo":null,"user_name":"MTg1KioqKioqNTQ="},{"cn_name":"\u767e\u5ea6\u5730\u56fe","comment_jump_url":"https:\/\/ugc.map.baidu.com\/cube\/comment\/choicepage?tab=1&uid=c4be2a16a63f3daf33621219&comment_sort=3","comment_photo":[],"content":"56iL5bqP6YO95piv5pm66IO955qE77yM5Y+v5Lul5YiG5p6Q5L2g55qE5oCn5qC85ZKM5Lmg5oOv77yB","date":"2019-12-07 05:39","one_url_mobile":null,"overall_rating":0,"user_logo":null,"user_name":"MTg1KioqKioqNTQ="}],"content_sug":{"search_ext_data":{"full_text":[]},"sug_ext_data":{"full_text":[],"sub_link_info":[]}},"default_image":"https:\/\/map-mobile-resource.cdn.bcebos.com\/icon\/rec\/search\/default\/huanzigongsiqiyetongyong.png","display_info_comment_label":{"hotel":"","life":""},"display_info_redu":"63","from_pds":"1","guoke_geo":{"geo":"4|12696487.868872,2574713.638773;12696663.867631,2574884.072928|1-12696529.3891105,2574884.0729276,12696663.8676306,2574815.1039170,12696615.8836495,2574713.6387730,12696487.8688719,2574791.6051821,12696529.3891105,2574884.0729276;","src_type":"wanneng_touchuan","sub_src":"guoke"},"heartbeat":{"comment":{"update_time":"1691839335","url":"baidumap:\/\/map\/place\/deepdetail?page=pinglun_page&pageTitle=\u7cbe\u9009\u8bc4\u8bba&pageParam={\"uid\":\"c4be2a16a63f3daf33621219\",\"cardParams\":{\"commenttab\":{}}}"},"transfer":1,"update_time":1691840585.8518},"image":"https:\/\/poi-pic.cdn.bcebos.com\/b2f9426975ec2ae6efc7a07c3d7a35b4.jpg","image_from":"ruitudetail","link":[],"mbc":{"markv":"1"},"name":"\u6df1\u8d85\u5149\u7535\u79d1\u6280\u56ed","navi_xy":{"bid":"7559314604288444209","diPoint":{"x":"12696575.430000","y":"2574800.520000"},"navi_info":[{"bid":"0","from":"","is_traffic":1,"name":"","navi_x":"12696401.867400","navi_y":"2574805.202840","reserve":{"navi_links":["1583249098"]},"uid":"2bfcb14cf5cb2cfcc23644f2"}],"navixy_src":"navi.navi_xy_gaojing_aoi","update_time":1699597658},"note":[],"overall_rating":"3.7","overall_rating_src":"dianping","phone":"(0755)28092999","phone_risk":{"bid":"7559314604288444209","word":"\u5982\u9047\u7535\u8bdd\u9519\u8bef\uff0c\u53ef\u70b9\u51fb\u201c\u62a5\u9519\u201d\u8fdb\u884c\u53cd\u9988"},"poi_address":"\u5e7f\u4e1c\u7701\u6df1\u5733\u5e02\u9f99\u534e\u533a\u9f99\u534e\u8857\u9053\u6c11\u79c0\u8def\u4e0e\u6e05\u79c0\u8def\u4ea4\u53c9\u53e3\u6b63\u4e1c\u65b9\u5411161\u7c73","poi_tags":{"dp_info":{"bad_comment_count":0,"comment_count":0,"common_comment_count":0,"envi":0,"good_comment_count":0,"overall":3.5,"price":0,"recommend_dish":[],"service":0,"tags":[],"taste":0}},"point":{"x":12696575.43,"y":2574800.53},"price":"","shop_hours_flag":"","std_tag":"\u516c\u53f8\u4f01\u4e1a;\u56ed\u533a","street":{"finepic":"","finepic_id":"","indoor_pano":"","interstartpid":"","ismodified":0,"navi_pano":[{"bubble_image":"https:\/\/quanjing-gif.cdn.bcebos.com\/navi\/88ab63835e9a4ef8c38a888a1f9649e5.gif","bubble_type":2,"mtime":1663925890,"navi_type":"single","navi_x":"12696401.98","navi_y":"2574805.08","pano_type":"street","pano_x":"12696392.01","pano_y":"2574804.28","pid":"09005700121709111601495098P","rctype":"bubble","view_dir":"0.92,0.19,0.33","view_dir_type":"3d","view_id":"e40e0a8f7dcf15631676432d"}],"pano":0,"pano_level":99,"street_gif_route_bubble":"","street_id":""},"tag":"\u56ed\u533a","taxi_info":{"drop_off_point":[{"bid":"16316773688201862056","ext_info":{"link_id":"15832490980","res_id":"72e62da29c524c3458e1df31e2a732ae","show_point":"12696408.53,2574815.32","type":"DOOR"},"name":"\u6df1\u8d85\u5149\u7535\u79d1\u6280\u56ed-\u5357\u5927\u95e8","x":"12696408.559","y":"2574815.30075"}],"status":"1"},"travel_info":{"navi_parking_relation":{"is_confi_aoi":1,"rec_parking_pv":[{"bid":"12166084647598150941","pv":34,"rate":100}],"rec_parkings":[{"distance":162,"is_children_parking":0,"is_confi_parking":0,"name":"\u505c\u8f66\u573a(\u6c11\u79c0\u8def)","std_tag":"\u4ea4\u901a\u8bbe\u65bd;\u505c\u8f66\u573a","uid":"fa3cc7f427b962b5fb2d6109"},{"distance":664,"is_children_parking":0,"is_confi_parking":0,"name":"\u5b89\u9521\u6052\u4f0d\u5c4b\u79d1\u6280\u5de5\u4e1a\u56ed\u897f\u5357\u4fa7\u505c\u8f66\u573a","std_tag":"\u4ea4\u901a\u8bbe\u65bd;\u505c\u8f66\u573a","uid":"0a79a8a29c6e64b7626858c3"}],"rec_pois":[],"transfer":1},"walk_gpoint":{"create_time":"1686356033","dest_gpoint":{"src_type":"public","sub_src":"public_xy_pujing_aoi","update_time":"1686356033","walk_info":[{"bind_feature":"0","gpoint_bid":"16316773688201862056","gpoint_name":"\u6df1\u8d85\u5149\u7535\u79d1\u6280\u56ed-\u5357\u5927\u95e8","risk":"1","update_time":"1686356033","walk_io_out":"0","walk_x":"12696408","walk_y":"2574815"}]},"gpoint_bid":"7559314604288444209","show_point":{"x":"12696575","y":"2574800"},"transfer":1,"update_time":"1686364493"}},"validate":0,"video":[],"vs_content":{"gray_line":{"realtime_computation":{"business_time":{"data":[],"data_exp":[],"src_name":"non_construct_qingxi","text":"","tip":[],"tips":[],"tpl_id":1,"tpl_name":"i"},"business_time_doc":{"common":{"reserved":"val"},"reserved":"val","search":{"reserved":"val"},"text":""},"week_time":{"reserved":"val","text":""}}},"invisible":{"bigdata":{"photo_album":[{"authorized":false,"icon_url":"https:\/\/map-mobile-lbsapp.cdn.bcebos.com\/tupian3x.png","jump_url":"baidumap:\/\/map\/place\/detail?popRoot=no&from=liebiao&uid=c4be2a16a63f3daf33621219&show_type=detail_page&poi_ext_param={\"anchor\":{\"cardName\": \"phototab\", \"cardParams\": {\"currentTab\": \"photo\"}}}","type":3,"url":"https:\/\/poi-pic.cdn.bcebos.com\/b2f9426975ec2ae6efc7a07c3d7a35b4.jpg?x-bce-process=image\/crop,x_125,y_0,w_750,h_563\/resize,m_fixed,w_960,h_720\/quality,q_80"},{"authorized":false,"icon_url":"https:\/\/map-mobile-lbsapp.cdn.bcebos.com\/tupian3x.png","jump_url":"baidumap:\/\/map\/place\/detail?popRoot=no&from=liebiao&uid=c4be2a16a63f3daf33621219&show_type=detail_page&poi_ext_param={\"anchor\":{\"cardName\": \"phototab\", \"cardParams\": {\"currentTab\": \"photo\"}}}","type":3,"url":"https:\/\/poi-pic.cdn.bcebos.com\/2af5e4a92e4c0ee2fdf0fc40fea4dbd6.jpg?x-bce-process=image\/crop,x_125,y_0,w_750,h_563\/resize,m_fixed,w_960,h_720\/quality,q_80"},{"authorized":true,"icon_url":"https:\/\/map-mobile-lbsapp.cdn.bcebos.com\/tupian3x.png","jump_url":"baidumap:\/\/map\/place\/detail?popRoot=no&from=liebiao&uid=c4be2a16a63f3daf33621219&show_type=detail_page&poi_ext_param={\"anchor\":{\"cardName\": \"phototab\", \"cardParams\": {\"currentTab\": \"photo\"}}}","type":3,"url":"http:\/\/lbsugc.cdn.bcebos.com\/images\/B64d76b51d03e41046b.jpeg?x-bce-process=image\/resize,m_fixed,w_960,h_720\/quality,q_80"},{"authorized":true,"icon_url":"https:\/\/map-mobile-lbsapp.cdn.bcebos.com\/tupian3x.png","jump_url":"baidumap:\/\/map\/place\/detail?popRoot=no&from=liebiao&uid=c4be2a16a63f3daf33621219&show_type=detail_page&poi_ext_param={\"anchor\":{\"cardName\": \"phototab\", \"cardParams\": {\"currentTab\": \"photo\"}}}","type":3,"url":"http:\/\/lbsugc.cdn.bcebos.com\/images\/B64d76b658f21efcdb.jpeg?x-bce-process=image\/resize,m_fixed,w_960,h_720\/quality,q_80"}],"photo_num":4,"showtag":"[[\"\\u56ed\\u533a\"], [\"\"], \"\", 0, \"\"]","tags1":"[[[\"63\\u4eba\\u8bbf\\u95ee\"], [\"\"], \"\", 1, \"\"]]"}},"map_image_service":{"labels_info":{"height":6}}}},"src_name":"enterprise"},"ext_display":{"display_info":{"catalog_fields":null,"impression_tag":{"hotel":"","life":""},"redu":"63","source_map":{"shop_hours":{"field_name":"webmining","priority":"0","uid":"7559314604288444209:webmining","update_time":"1549831099.057"}},"src_name":"display_info","uids":["7559314604288444209:redu","13236526282913045087:redu","7559314604288444209:audit","7559314604288444209:business_time","7559314604288444209:webmining","7559314604288444209:zhukapian","11390894217651625308"]}},"ext_type":4,"f_flag":8,"father_son":0,"gbrank_score":-8.935178928701,"geo":"1|12696575.43,2574800.52;12696575.43,2574800.52|12696575.43,2574800.52;","geo_type":0,"history_address":"\u6df1\u5733\u5e02","hit_tag_press":0,"indoor_pano":"","is_nearnest_nat":0,"is_top_nat":0,"ismodified":0,"name":"\u6df1\u8d85\u5149\u7535\u79d1\u6280\u56ed","navi_update_time":1704706631,"navi_x":"12696401.8674","navi_y":"2574805.20284","new_catalog_id":"0c0000","pano":0,"poiType":0,"poi_click_num":0,"poi_profile":1,"primary_uid":"7559314604288444209","prio_flag":32,"qu_brandid":0,"query_guide":"[{\"icon\":\"https:\\\/\\\/map-mobile-resource.cdn.bcebos.com\\\/icon\\\/service\\\/search\\\/default\\\/meishi5.png\",\"text\":\"\u7f8e\u98df\",\"type\":1},{\"icon\":\"https:\\\/\\\/map-mobile-resource.cdn.bcebos.com\\\/icon\\\/rec\\\/search\\\/default\\\/jiudian.png\",\"text\":\"\u9152\u5e97\",\"type\":1},{\"icon\":\"https:\\\/\\\/map-mobile-resource.cdn.bcebos.com\\\/icon\\\/rec\\\/search\\\/default\\\/jingdian.png\",\"text\":\"\u666f\u70b9\",\"type\":1},{\"icon\":\"https:\\\/\\\/map-mobile-resource.cdn.bcebos.com\\\/icon\\\/rec\\\/search\\\/default\\\/tingchechang.png\",\"text\":\"\u505c\u8f66\u573a\",\"type\":1},{\"icon\":\"https:\\\/\\\/map-mobile-resource.cdn.bcebos.com\\\/icon\\\/rec\\\/search\\\/default\\\/xiuxianyule.png\",\"text\":\"\u4f11\u95f2\u5a31\u4e50\",\"type\":1},{\"icon\":\"https:\\\/\\\/map-mobile-resource.cdn.bcebos.com\\\/icon\\\/service\\\/search\\\/default\\\/gouwu5.png\",\"text\":\"\u8d2d\u7269\",\"type\":1},{\"icon\":\"https:\\\/\\\/map-mobile-resource.cdn.bcebos.com\\\/icon\\\/rec\\\/search\\\/default\\\/jiayou.png\",\"text\":\"\u52a0\u6cb9\u7ad9\",\"type\":1}]","route_flag":0,"show_tag":[],"status":1,"std_tag":"\u516c\u53f8\u4f01\u4e1a;\u56ed\u533a","std_tag_id":"2500","storage_src":"api","street_id":"","tag":"\u516c\u53f8\u4f01\u4e1a \u65c5\u6e38<font color=\"#c60a00\">\u666f\u70b9<\/font>","tel":"(0755)28092999","title_color_shows":[],"top1_reinforce":0,"ty":0,"uid":"c4be2a16a63f3daf33621219","view_type":9,"x":1269657543,"y":257480052},{"acc_flag":0,"addr":"\u6df1\u5733\u5e02\u9f99\u534e\u533a\u88d5\u65b0\u8def\u6df1\u5733\u6052\u6e56\u5546\u52a1\u9152\u5e97\u4e1c\u5317\u4fa7","addr_hot_percent":0,"address_color_shows":[{"end":12,"name":"\u6df1\u5733\u5e02\u9f99\u534e\u533a","start":0},{"end":22,"name":"\u6df1\u5733","start":18}],"address_norm":"[\u5e7f\u4e1c\u7701(440000)|PROV|0|][\u6df1\u5733\u5e02(440300)|CITY|1|][\u9f99\u534e\u533a(440309)|AREA|1|][\u88d5\u65b0\u8def()|ROAD|1|]\u6df1\u5733\u6052\u6e56\u5546\u52a1\u9152\u5e97\u4e1c\u5317\u4fa7","admin_info":{"area_id":440309,"area_name":"\u9f99\u534e\u533a","city_id":440300,"city_name":"\u6df1\u5733\u5e02","province_id":440000,"province_name":"\u5e7f\u4e1c\u7701","town_id":440309004,"town_name":"\u89c2\u6f9c\u8857\u9053"},"api_admin_info":{"area_code":3352,"area_name":"\u9f99\u534e\u533a","city_code":340,"city_name":"\u6df1\u5733\u5e02","prov_code":7,"prov_name":"\u5e7f\u4e1c\u7701"},"area":3352,"area_name":"\u6df1\u5733\u5e02\u9f99\u534e\u533a","biz_type":0,"brand_id":null,"catalogID":0,"city_id":340,"city_name":"\u6df1\u5733\u5e02","cla":[],"class_similar_score":0.65190923213959,"click_flag":0,"detail":1,"diPointX":1270181613,"diPointY":258460815,"di_tag":"\u65c5\u6e38\u666f\u70b9 \u516c\u56ed","dis":-1,"dist2route":0,"dist2start":0,"ernie_score":0,"ext":{"detail_info":{"areaid":"3352","bubble_info":{"icon":{"dark_icon_url":null,"icon_url":null,"std_tag":"\u65c5\u6e38\u666f\u70b9;\u516c\u56ed"},"mark":null,"sub_title":null,"tag":null,"title":null},"content_sug":{"search_ext_data":{"full_text":[]},"sug_ext_data":{"full_text":[],"sub_link_info":[]}},"default_image":"https:\/\/map-mobile-resource.cdn.bcebos.com\/icon\/rec\/search\/default\/huanzigongyuan.png","from_pds":"1","image":"https:\/\/map-mobile-resource.cdn.bcebos.com\/icon\/rec\/search\/default\/huanzigongyuan.png","is_default_image":"1","mbc":{"markv":"1"},"name":"\u5927\u6c34\u7530\u8857\u5fc3\u516c\u56ed","phone":"","poi_address":"\u6df1\u5733\u5e02\u9f99\u534e\u533a\u88d5\u65b0\u8def\u6df1\u5733\u6052\u6e56\u5546\u52a1\u9152\u5e97\u4e1c\u5317\u4fa7","point":{"x":12701816.13,"y":2584608.15},"short_desc":"","std_tag":"\u65c5\u6e38\u666f\u70b9;\u516c\u56ed","tag":"\u65c5\u6e38\u666f\u70b9 \u516c\u56ed","vs_content":{"invisible":{"bigdata":{"showtag":"[[\"\\u516c\\u56ed\"], [\"\"], \"\", 0, \"\"]"}}}},"src_name":"scope"},"ext_display":null,"ext_type":4,"f_flag":8,"father_son":0,"gbrank_score":-8.9595276964863,"geo":"1|12701816.13,2584608.15;12701816.13,2584608.15|12701816.13,2584608.15;","geo_type":0,"history_address":"\u6df1\u5733\u5e02","hit_tag_press":0,"is_nearnest_nat":0,"is_top_nat":0,"name":"\u5927\u6c34\u7530\u8857\u5fc3\u516c\u56ed","navi_update_time":1689956589,"navi_x":"0","navi_y":"0","new_catalog_id":"0c0100","poiType":0,"poi_click_num":0,"poi_profile":0,"primary_uid":"94817563745458555","prio_flag":32,"qu_brandid":0,"query_guide":"[{\"icon\":\"https:\\\/\\\/map-mobile-resource.cdn.bcebos.com\\\/icon\\\/service\\\/search\\\/default\\\/meishi5.png\",\"text\":\"\u7f8e\u98df\",\"type\":1},{\"icon\":\"https:\\\/\\\/map-mobile-resource.cdn.bcebos.com\\\/icon\\\/rec\\\/search\\\/default\\\/jiudian.png\",\"text\":\"\u9152\u5e97\",\"type\":1},{\"icon\":\"https:\\\/\\\/map-mobile-resource.cdn.bcebos.com\\\/icon\\\/rec\\\/search\\\/default\\\/jingdian.png\",\"text\":\"\u666f\u70b9\",\"type\":1},{\"icon\":\"https:\\\/\\\/map-mobile-resource.cdn.bcebos.com\\\/icon\\\/rec\\\/search\\\/default\\\/tingchechang.png\",\"text\":\"\u505c\u8f66\u573a\",\"type\":1},{\"icon\":\"https:\\\/\\\/map-mobile-resource.cdn.bcebos.com\\\/icon\\\/rec\\\/search\\\/default\\\/xiuxianyule.png\",\"text\":\"\u4f11\u95f2\u5a31\u4e50\",\"type\":1},{\"icon\":\"https:\\\/\\\/map-mobile-resource.cdn.bcebos.com\\\/icon\\\/service\\\/search\\\/default\\\/gouwu5.png\",\"text\":\"\u8d2d\u7269\",\"type\":1},{\"icon\":\"https:\\\/\\\/map-mobile-resource.cdn.bcebos.com\\\/icon\\\/rec\\\/search\\\/default\\\/jiayou.png\",\"text\":\"\u52a0\u6cb9\u7ad9\",\"type\":1}]","route_flag":0,"show_tag":[],"status":1,"std_tag":"\u65c5\u6e38\u666f\u70b9;\u516c\u56ed","std_tag_id":"1502","storage_src":"api","tag":"\u65c5\u6e38<font color=\"#c60a00\">\u666f\u70b9<\/font> \u516c\u56ed","title_color_shows":[],"top1_reinforce":0,"ty":0,"uid":"d80418e7d8166358ad31e50f","view_type":0,"x":1270181613,"y":258460815},{"acc_flag":0,"addr":"\u6df1\u5733\u5e02\u9f99\u534e\u533a\u534e\u5357\u8def\u6df1\u56fd\u9645\u534e\u5357\u7269\u6d41","addr_hot_percent":0,"address_color_shows":[{"end":12,"name":"\u6df1\u5733\u5e02\u9f99\u534e\u533a","start":0}],"address_norm":"[\u5e7f\u4e1c\u7701(440000)|PROV|0|][\u6df1\u5733\u5e02(440300)|CITY|1|][\u9f99\u534e\u533a(440309)|AREA|1|][\u534e\u5357\u8def()|ROAD|1|]\u6df1\u56fd\u9645\u534e\u5357\u7269\u6d41","admin_info":{"area_id":440309,"area_name":"\u9f99\u534e\u533a","city_id":440300,"city_name":"\u6df1\u5733\u5e02","province_id":440000,"province_name":"\u5e7f\u4e1c\u7701","town_id":440309003,"town_name":"\u6c11\u6cbb\u8857\u9053"},"aoi":"\u9f99\u534e","api_admin_info":{"area_code":3352,"area_name":"\u9f99\u534e\u533a","city_code":340,"city_name":"\u6df1\u5733\u5e02","prov_code":7,"prov_name":"\u5e7f\u4e1c\u7701"},"area":3352,"area_name":"\u6df1\u5733\u5e02\u9f99\u534e\u533a","biz_type":0,"brand_id":null,"catalogID":0,"city_id":340,"city_name":"\u6df1\u5733\u5e02","cla":[],"class_similar_score":0.74947339296341,"click_flag":0,"detail":1,"diPointX":1269730588,"diPointY":256978185,"di_tag":"\u65c5\u6e38\u666f\u70b9 \u516c\u56ed","dis":-1,"dist2route":0,"dist2start":0,"ernie_score":0,"ext":{"detail_info":{"areaid":"3352","bubble_info":{"icon":{"dark_icon_url":null,"icon_url":null,"std_tag":"\u65c5\u6e38\u666f\u70b9;\u516c\u56ed"},"mark":null,"sub_title":null,"tag":null,"title":null},"content_sug":{"search_ext_data":{"full_text":[]},"sug_ext_data":{"full_text":[],"sub_link_info":[]}},"default_image":"https:\/\/map-mobile-resource.cdn.bcebos.com\/icon\/rec\/search\/default\/huanzigongyuan.png","from_pds":"1","image":"https:\/\/map-mobile-resource.cdn.bcebos.com\/icon\/rec\/search\/default\/huanzigongyuan.png","is_default_image":"1","mbc":{"markv":"1"},"name":"\u9f99\u534e\u540d\u516c\u56ed","phone":"","poi_address":"\u6df1\u5733\u5e02\u9f99\u534e\u533a\u534e\u5357\u8def\u6df1\u56fd\u9645\u534e\u5357\u7269\u6d41","point":{"x":12697305.88,"y":2569781.85},"short_desc":"","std_tag":"\u65c5\u6e38\u666f\u70b9;\u516c\u56ed","tag":"\u65c5\u6e38\u666f\u70b9 \u516c\u56ed","vs_content":{"invisible":{"bigdata":{"showtag":"[[\"\\u516c\\u56ed\"], [\"\"], \"\", 0, \"\"]"}}}},"src_name":"scope"},"ext_display":null,"ext_type":4,"f_flag":8,"father_son":0,"gbrank_score":-8.9595276964863,"geo":"1|12697305.88,2569781.85;12697305.88,2569781.85|12697305.88,2569781.85;","geo_type":0,"history_address":"\u6df1\u5733\u5e02","hit_tag_press":0,"is_nearnest_nat":0,"is_top_nat":0,"name":"\u9f99\u534e\u540d\u516c\u56ed","navi_update_time":1689092225,"navi_x":"0","navi_y":"0","new_catalog_id":"0c0100","poiType":0,"poi_click_num":0,"poi_profile":0,"primary_uid":"15381482982021541291","prio_flag":32,"qu_brandid":0,"query_guide":"[{\"icon\":\"https:\\\/\\\/map-mobile-resource.cdn.bcebos.com\\\/icon\\\/service\\\/search\\\/default\\\/meishi5.png\",\"text\":\"\u7f8e\u98df\",\"type\":1},{\"icon\":\"https:\\\/\\\/map-mobile-resource.cdn.bcebos.com\\\/icon\\\/rec\\\/search\\\/default\\\/jiudian.png\",\"text\":\"\u9152\u5e97\",\"type\":1},{\"icon\":\"https:\\\/\\\/map-mobile-resource.cdn.bcebos.com\\\/icon\\\/rec\\\/search\\\/default\\\/jingdian.png\",\"text\":\"\u666f\u70b9\",\"type\":1},{\"icon\":\"https:\\\/\\\/map-mobile-resource.cdn.bcebos.com\\\/icon\\\/rec\\\/search\\\/default\\\/tingchechang.png\",\"text\":\"\u505c\u8f66\u573a\",\"type\":1},{\"icon\":\"https:\\\/\\\/map-mobile-resource.cdn.bcebos.com\\\/icon\\\/rec\\\/search\\\/default\\\/xiuxianyule.png\",\"text\":\"\u4f11\u95f2\u5a31\u4e50\",\"type\":1},{\"icon\":\"https:\\\/\\\/map-mobile-resource.cdn.bcebos.com\\\/icon\\\/service\\\/search\\\/default\\\/gouwu5.png\",\"text\":\"\u8d2d\u7269\",\"type\":1},{\"icon\":\"https:\\\/\\\/map-mobile-resource.cdn.bcebos.com\\\/icon\\\/rec\\\/search\\\/default\\\/jiayou.png\",\"text\":\"\u52a0\u6cb9\u7ad9\",\"type\":1}]","route_flag":0,"show_tag":[],"status":1,"std_tag":"\u65c5\u6e38\u666f\u70b9;\u516c\u56ed","std_tag_id":"1502","storage_src":"api","tag":"\u65c5\u6e38<font color=\"#c60a00\">\u666f\u70b9<\/font> \u516c\u56ed","title_color_shows":[{"end":4,"name":"\u9f99\u534e","start":0}],"top1_reinforce":0,"ty":0,"uid":"fbc8069a0d15ec4f4007c1c1","view_type":0,"x":1269730588,"y":256978185},{"acc_flag":0,"addr":"\u6df1\u5733\u5e02\u9f99\u534e\u533a\u4e0a\u56f4\u8def\u91d1\u5021\u8fbe\u79d1\u6280\u56ed\u4e1c\u5357\u4fa7\u7ea6260\u7c73","addr_hot_percent":0,"address_color_shows":[{"end":12,"name":"\u6df1\u5733\u5e02\u9f99\u534e\u533a","start":0}],"address_norm":"[\u5e7f\u4e1c\u7701(440000)|PROV|0|][\u6df1\u5733\u5e02(440300)|CITY|1|][\u9f99\u534e\u533a(440309)|AREA|1|][\u4e0a\u56f4\u8def()|ROAD|1|]\u91d1\u5021\u8fbe\u79d1\u6280\u56ed\u4e1c\u5357\u4fa7\u7ea6260\u7c73","admin_info":{"area_id":440309,"area_name":"\u9f99\u534e\u533a","city_id":440300,"city_name":"\u6df1\u5733\u5e02","province_id":440000,"province_name":"\u5e7f\u4e1c\u7701","town_id":440309001,"town_name":"\u89c2\u6e56\u8857\u9053"},"api_admin_info":{"area_code":3352,"area_name":"\u9f99\u534e\u533a","city_code":340,"city_name":"\u6df1\u5733\u5e02","prov_code":7,"prov_name":"\u5e7f\u4e1c\u7701"},"area":3352,"area_name":"\u6df1\u5733\u5e02\u9f99\u534e\u533a","biz_type":0,"brand_id":null,"catalogID":0,"city_id":340,"city_name":"\u6df1\u5733\u5e02","cla":[],"class_similar_score":0,"click_flag":0,"detail":1,"diPointX":1270072245,"diPointY":257746565,"di_tag":"\u65c5\u6e38\u666f\u70b9 \u516c\u56ed","dis":-1,"dist2route":0,"dist2start":0,"ernie_score":0,"ext":{"detail_info":{"areaid":"3352","bubble_info":{"icon":{"dark_icon_url":null,"icon_url":null,"std_tag":"\u65c5\u6e38\u666f\u70b9;\u516c\u56ed"},"mark":null,"sub_title":null,"tag":null,"title":null},"content_sug":{"search_ext_data":{"full_text":[]},"sug_ext_data":{"full_text":[],"sub_link_info":[]}},"default_image":"https:\/\/map-mobile-resource.cdn.bcebos.com\/icon\/rec\/search\/default\/huanzigongyuan.png","from_pds":"1","image":"https:\/\/map-mobile-resource.cdn.bcebos.com\/icon\/rec\/search\/default\/huanzigongyuan.png","is_default_image":"1","mbc":{"markv":"1"},"name":"\u86c7\u5730\u5751\u516c\u56ed","phone":"","poi_address":"\u6df1\u5733\u5e02\u9f99\u534e\u533a\u4e0a\u56f4\u8def\u91d1\u5021\u8fbe\u79d1\u6280\u56ed\u4e1c\u5357\u4fa7\u7ea6260\u7c73","point":{"x":12700722.45,"y":2577465.65},"short_desc":"","std_tag":"\u65c5\u6e38\u666f\u70b9;\u516c\u56ed","tag":"\u65c5\u6e38\u666f\u70b9 \u516c\u56ed","vs_content":{"invisible":{"bigdata":{"showtag":"[[\"\\u516c\\u56ed\"], [\"\"], \"\", 0, \"\"]"}}}},"src_name":"scope"},"ext_display":null,"ext_type":4,"f_flag":8,"father_son":0,"gbrank_score":-8.9595276964863,"geo":"1|12700722.45,2577465.65;12700722.45,2577465.65|12700722.45,2577465.65;","geo_type":0,"history_address":"\u6df1\u5733\u5e02","hit_tag_press":0,"is_nearnest_nat":0,"is_top_nat":0,"name":"\u86c7\u5730\u5751\u516c\u56ed","navi_update_time":1696385929,"navi_x":"0","navi_y":"0","new_catalog_id":"0c0100","poiType":0,"poi_click_num":0,"poi_profile":0,"primary_uid":"14674563852512978616","prio_flag":32,"qu_brandid":0,"query_guide":"[{\"icon\":\"https:\\\/\\\/map-mobile-resource.cdn.bcebos.com\\\/icon\\\/service\\\/search\\\/default\\\/meishi5.png\",\"text\":\"\u7f8e\u98df\",\"type\":1},{\"icon\":\"https:\\\/\\\/map-mobile-resource.cdn.bcebos.com\\\/icon\\\/rec\\\/search\\\/default\\\/jiudian.png\",\"text\":\"\u9152\u5e97\",\"type\":1},{\"icon\":\"https:\\\/\\\/map-mobile-resource.cdn.bcebos.com\\\/icon\\\/rec\\\/search\\\/default\\\/jingdian.png\",\"text\":\"\u666f\u70b9\",\"type\":1},{\"icon\":\"https:\\\/\\\/map-mobile-resource.cdn.bcebos.com\\\/icon\\\/rec\\\/search\\\/default\\\/tingchechang.png\",\"text\":\"\u505c\u8f66\u573a\",\"type\":1},{\"icon\":\"https:\\\/\\\/map-mobile-resource.cdn.bcebos.com\\\/icon\\\/rec\\\/search\\\/default\\\/xiuxianyule.png\",\"text\":\"\u4f11\u95f2\u5a31\u4e50\",\"type\":1},{\"icon\":\"https:\\\/\\\/map-mobile-resource.cdn.bcebos.com\\\/icon\\\/service\\\/search\\\/default\\\/gouwu5.png\",\"text\":\"\u8d2d\u7269\",\"type\":1},{\"icon\":\"https:\\\/\\\/map-mobile-resource.cdn.bcebos.com\\\/icon\\\/rec\\\/search\\\/default\\\/jiayou.png\",\"text\":\"\u52a0\u6cb9\u7ad9\",\"type\":1}]","route_flag":0,"show_tag":[],"status":1,"std_tag":"\u65c5\u6e38\u666f\u70b9;\u516c\u56ed","std_tag_id":"1502","storage_src":"api","tag":"\u65c5\u6e38<font color=\"#c60a00\">\u666f\u70b9<\/font> \u516c\u56ed","title_color_shows":[],"top1_reinforce":0,"ty":0,"uid":"2e0a28c28d33ae5f715e800a","view_type":0,"x":1270072245,"y":257746565},{"acc_flag":0,"addr":"\u5e7f\u4e1c\u7701\u6df1\u5733\u5e02\u9f99\u534e\u533a\u89c2\u5174\u897f\u8def","addr_hot_percent":0,"address_color_shows":[{"end":18,"name":"\u6df1\u5733\u5e02\u9f99\u534e\u533a","start":6}],"address_norm":"[\u5e7f\u4e1c\u7701(440000)|PROV|1|][\u6df1\u5733\u5e02(440300)|CITY|1|][\u9f99\u534e\u533a(440309)|AREA|1|][\u89c2\u5174\u897f\u8def()|ROAD|1|]","admin_info":{"area_id":440309,"area_name":"\u9f99\u534e\u533a","city_id":440300,"city_name":"\u6df1\u5733\u5e02","province_id":440000,"province_name":"\u5e7f\u4e1c\u7701","town_id":440309005,"town_name":"\u798f\u57ce\u8857\u9053"},"aoi":"\u89c2\u6f9c","api_admin_info":{"area_code":3352,"area_name":"\u9f99\u534e\u533a","city_code":340,"city_name":"\u6df1\u5733\u5e02","prov_code":7,"prov_name":"\u5e7f\u4e1c\u7701"},"area":3352,"area_name":"\u6df1\u5733\u5e02\u9f99\u534e\u533a","biz_type":0,"brand_id":null,"catalogID":0,"city_id":340,"city_name":"\u6df1\u5733\u5e02","cla":[],"class_similar_score":0,"click_flag":0,"detail":1,"diPointX":1269479599,"diPointY":257969121,"di_tag":"\u65c5\u6e38\u666f\u70b9 \u516c\u56ed","dis":-1,"dist2route":0,"dist2start":0,"ernie_score":0,"ext":{"detail_info":{"areaid":"3352","bubble_info":{"icon":{"dark_icon_url":null,"icon_url":null,"std_tag":"\u65c5\u6e38\u666f\u70b9;\u516c\u56ed"},"mark":null,"sub_title":null,"tag":null,"title":null},"content_sug":{"search_ext_data":{"full_text":[]},"sug_ext_data":{"full_text":[],"sub_link_info":[]}},"default_image":"https:\/\/map-mobile-resource.cdn.bcebos.com\/icon\/rec\/search\/default\/huanzigongyuan.png","from_pds":"1","image":"https:\/\/map-mobile-resource.cdn.bcebos.com\/icon\/rec\/search\/default\/huanzigongyuan.png","is_default_image":"1","mbc":{"markv":"1"},"name":"\u798f\u57ce\u594b\u6597\u8005\u516c\u56ed","phone":"","poi_address":"\u5e7f\u4e1c\u7701\u6df1\u5733\u5e02\u9f99\u534e\u533a\u89c2\u5174\u897f\u8def","point":{"x":12694795.99,"y":2579691.21},"short_desc":"","std_tag":"\u65c5\u6e38\u666f\u70b9;\u516c\u56ed","tag":"\u65c5\u6e38\u666f\u70b9 \u516c\u56ed","vs_content":{"invisible":{"bigdata":{"showtag":"[[\"\\u516c\\u56ed\"], [\"\"], \"\", 0, \"\"]"}}}},"src_name":"scope"},"ext_display":null,"ext_type":4,"f_flag":8,"father_son":0,"gbrank_score":-8.9595276964863,"geo":"1|12694795.99,2579691.21;12694795.99,2579691.21|12694795.99,2579691.21;","geo_type":0,"history_address":"\u6df1\u5733\u5e02","hit_tag_press":0,"is_nearnest_nat":0,"is_top_nat":0,"name":"\u798f\u57ce\u594b\u6597\u8005\u516c\u56ed","navi_update_time":1705315372,"navi_x":"0","navi_y":"0","new_catalog_id":"0c0100","poiType":0,"poi_click_num":0,"poi_profile":0,"primary_uid":"179429378288771267","prio_flag":32,"qu_brandid":0,"query_guide":"[{\"icon\":\"https:\\\/\\\/map-mobile-resource.cdn.bcebos.com\\\/icon\\\/service\\\/search\\\/default\\\/meishi5.png\",\"text\":\"\u7f8e\u98df\",\"type\":1},{\"icon\":\"https:\\\/\\\/map-mobile-resource.cdn.bcebos.com\\\/icon\\\/rec\\\/search\\\/default\\\/jiudian.png\",\"text\":\"\u9152\u5e97\",\"type\":1},{\"icon\":\"https:\\\/\\\/map-mobile-resource.cdn.bcebos.com\\\/icon\\\/rec\\\/search\\\/default\\\/jingdian.png\",\"text\":\"\u666f\u70b9\",\"type\":1},{\"icon\":\"https:\\\/\\\/map-mobile-resource.cdn.bcebos.com\\\/icon\\\/rec\\\/search\\\/default\\\/tingchechang.png\",\"text\":\"\u505c\u8f66\u573a\",\"type\":1},{\"icon\":\"https:\\\/\\\/map-mobile-resource.cdn.bcebos.com\\\/icon\\\/rec\\\/search\\\/default\\\/xiuxianyule.png\",\"text\":\"\u4f11\u95f2\u5a31\u4e50\",\"type\":1},{\"icon\":\"https:\\\/\\\/map-mobile-resource.cdn.bcebos.com\\\/icon\\\/service\\\/search\\\/default\\\/gouwu5.png\",\"text\":\"\u8d2d\u7269\",\"type\":1},{\"icon\":\"https:\\\/\\\/map-mobile-resource.cdn.bcebos.com\\\/icon\\\/rec\\\/search\\\/default\\\/jiayou.png\",\"text\":\"\u52a0\u6cb9\u7ad9\",\"type\":1}]","route_flag":0,"show_tag":[],"status":1,"std_tag":"\u65c5\u6e38\u666f\u70b9;\u516c\u56ed","std_tag_id":"1502","storage_src":"api","tag":"\u65c5\u6e38<font color=\"#c60a00\">\u666f\u70b9<\/font> \u516c\u56ed","title_color_shows":[],"top1_reinforce":0,"ty":0,"uid":"ae438153fa7b75ba5a3ac8ef","view_type":0,"x":1269479599,"y":257969121},{"acc_flag":0,"addr":"\u6df1\u5733\u5e02\u9f99\u534e\u533a\u56ed\u53d1\u8def\u65b0\u767e\u4e3d\u5de5\u4e1a\u56ed\u4e1c\u5357\u4fa7\u7ea6130\u7c73","addr_hot_percent":0,"address_color_shows":[{"end":12,"name":"\u6df1\u5733\u5e02\u9f99\u534e\u533a","start":0}],"address_norm":"[\u5e7f\u4e1c\u7701(440000)|PROV|0|][\u6df1\u5733\u5e02(440300)|CITY|1|][\u9f99\u534e\u533a(440309)|AREA|1|][\u56ed\u53d1\u8def()|ROAD|1|]\u65b0\u767e\u4e3d\u5de5\u4e1a\u56ed\u4e1c\u5357\u4fa7\u7ea6130\u7c73","admin_info":{"area_id":440309,"area_name":"\u9f99\u534e\u533a","city_id":440300,"city_name":"\u6df1\u5733\u5e02","province_id":440000,"province_name":"\u5e7f\u4e1c\u7701","town_id":440309004,"town_name":"\u5927\u6d6a\u8857\u9053"},"aoi":"\u5927\u6d6a;\u9f99\u534e","api_admin_info":{"area_code":3352,"area_name":"\u9f99\u534e\u533a","city_code":340,"city_name":"\u6df1\u5733\u5e02","prov_code":7,"prov_name":"\u5e7f\u4e1c\u7701"},"area":3352,"area_name":"\u6df1\u5733\u5e02\u9f99\u534e\u533a","biz_type":0,"brand_id":null,"catalogID":0,"city_id":340,"city_name":"\u6df1\u5733\u5e02","cla":[],"class_similar_score":0,"click_flag":0,"detail":1,"diPointX":1268964819,"diPointY":257806710,"di_tag":"\u65c5\u6e38\u666f\u70b9 \u516c\u56ed","dis":-1,"dist2route":0,"dist2start":0,"ernie_score":0,"ext":{"detail_info":{"areaid":"3352","bubble_info":{"icon":{"dark_icon_url":null,"icon_url":null,"std_tag":"\u65c5\u6e38\u666f\u70b9;\u516c\u56ed"},"mark":null,"sub_title":null,"tag":null,"title":null},"content_sug":{"search_ext_data":{"full_text":[]},"sug_ext_data":{"full_text":[],"sub_link_info":[]}},"default_image":"https:\/\/map-mobile-resource.cdn.bcebos.com\/icon\/rec\/search\/default\/huanzigongyuan.png","from_pds":"1","guoke_geo":{"geo":"4|12689468.636867,2577953.579808;12689776.372906,2578127.871694|1-12689468.9011862,2578010.9576665,12689485.4604736,2577957.5761873,12689485.8813831,2577956.5263967,12689486.4911461,2577955.5993195,12689487.2453756,2577954.8183095,12689488.1329917,2577954.2072020,12689489.6312901,2577953.6528967,12689491.2188582,2577953.5798077,12689492.7624772,2577953.9980114,12689623.8709280,2578015.5146731,12689644.4077045,2578020.9996551,12689645.5628725,2578021.3391494,12689646.6733798,2578021.4140655,12689647.7836553,2578021.2369994,12689649.0380140,2578020.7618932,12689650.6034470,2578020.4469301,12689652.1804540,2578020.6360477,12689653.6468398,2578021.2796153,12689654.5136224,2578021.9631401,12689655.2472945,2578022.8008614,12689655.8145195,2578023.7683379,12689656.4042206,2578025.0240797,12689657.1047910,2578026.0893233,12689657.6277093,2578027.1761872,12689657.9397055,2578028.3322232,12689658.0296636,2578029.5452857,12689657.8422598,2578031.0306109,12689657.7322779,2578032.1810091,12689657.8332848,2578033.3342264,12689658.1341424,2578034.4541177,12689658.6348068,2578035.4926867,12689659.3019197,2578036.4014917,12689660.1243660,2578037.1683834,12689661.2465407,2578037.8312811,12689773.4243928,2578088.8756078,12689774.3245970,2578089.5348551,12689775.1027872,2578090.3605449,12689775.7034203,2578091.3399827,12689776.1264409,2578092.4131769,12689776.3496250,2578093.5678511,12689776.3729062,2578094.7320136,12689776.1740499,2578095.8813879,12689775.7752138,2578096.9562581,12689762.2294433,2578125.1863143,12689761.5861009,2578126.0660729,12689760.3431833,2578127.1062157,12689758.8777622,2578127.7235732,12689757.3119614,2578127.8716938,12689755.7568310,2578127.5399860,12689637.0240555,2578081.9611986,12689635.8800610,2578081.6817824,12689634.7807172,2578081.6549326,12689633.7037932,2578081.8563522,12689632.6937172,2578082.2986414,12689631.6394126,2578082.9443023,12689630.1408269,2578083.4639532,12689628.5529684,2578083.5024337,12689627.0201820,2578083.0497003,12689626.0758241,2578082.4969497,12689625.2534483,2578081.7658696,12689624.5752848,2578080.8807611,12689624.0635748,2578079.8779242,12689623.6516925,2578078.7564555,12689623.1066591,2578077.7411641,12689622.3840913,2578076.8674414,12689621.5284172,2578076.1478875,12689620.3619374,2578075.5440866,12689472.3721003,2578018.5792659,12689471.3835541,2578018.0849512,12689470.5058427,2578017.3882665,12689469.7722946,2578016.5136958,12689469.1940672,2578015.5213965,12689468.8155690,2578014.4120165,12689468.6368666,2578013.2575498,12689468.6690953,2578012.0941550,12689468.9011862,2578010.9576665;","is_precise":0,"src_type":"wanneng_touchuan","sub_src":"guoke"},"image":"https:\/\/map-mobile-resource.cdn.bcebos.com\/icon\/rec\/search\/default\/huanzigongyuan.png","is_default_image":"1","mbc":{"markv":"1"},"name":"\u540c\u5bcc\u88d5\u793e\u533a\u516c\u56ed(\u56ed\u53d1\u8def)","phone":"","poi_address":"\u6df1\u5733\u5e02\u9f99\u534e\u533a\u56ed\u53d1\u8def\u65b0\u767e\u4e3d\u5de5\u4e1a\u56ed\u4e1c\u5357\u4fa7\u7ea6130\u7c73","point":{"x":12689648.19,"y":2578067.1},"short_desc":"","std_tag":"\u65c5\u6e38\u666f\u70b9;\u516c\u56ed","tag":"\u65c5\u6e38\u666f\u70b9 \u516c\u56ed","vs_content":{"invisible":{"bigdata":{"showtag":"[[\"\\u516c\\u56ed\"], [\"\"], \"\", 0, \"\"]"}}}},"src_name":"scope"},"ext_display":null,"ext_type":4,"f_flag":8,"father_son":0,"gbrank_score":-8.9595276964863,"geo":"1|12689648.19,2578067.10;12689648.19,2578067.10|12689648.19,2578067.10;","geo_type":0,"history_address":"\u6df1\u5733\u5e02","hit_tag_press":0,"is_nearnest_nat":0,"is_top_nat":0,"name":"\u540c\u5bcc\u88d5\u793e\u533a\u516c\u56ed(\u56ed\u53d1\u8def)","navi_update_time":1697882343,"navi_x":"0","navi_y":"0","new_catalog_id":"0c0100","poiType":0,"poi_click_num":0,"poi_profile":1,"primary_uid":"792681825609137466","prio_flag":32,"qu_brandid":0,"query_guide":"[{\"icon\":\"https:\\\/\\\/map-mobile-resource.cdn.bcebos.com\\\/icon\\\/service\\\/search\\\/default\\\/meishi5.png\",\"text\":\"\u7f8e\u98df\",\"type\":1},{\"icon\":\"https:\\\/\\\/map-mobile-resource.cdn.bcebos.com\\\/icon\\\/rec\\\/search\\\/default\\\/jiudian.png\",\"text\":\"\u9152\u5e97\",\"type\":1},{\"icon\":\"https:\\\/\\\/map-mobile-resource.cdn.bcebos.com\\\/icon\\\/rec\\\/search\\\/default\\\/jingdian.png\",\"text\":\"\u666f\u70b9\",\"type\":1},{\"icon\":\"https:\\\/\\\/map-mobile-resource.cdn.bcebos.com\\\/icon\\\/rec\\\/search\\\/default\\\/tingchechang.png\",\"text\":\"\u505c\u8f66\u573a\",\"type\":1},{\"icon\":\"https:\\\/\\\/map-mobile-resource.cdn.bcebos.com\\\/icon\\\/rec\\\/search\\\/default\\\/xiuxianyule.png\",\"text\":\"\u4f11\u95f2\u5a31\u4e50\",\"type\":1},{\"icon\":\"https:\\\/\\\/map-mobile-resource.cdn.bcebos.com\\\/icon\\\/service\\\/search\\\/default\\\/gouwu5.png\",\"text\":\"\u8d2d\u7269\",\"type\":1},{\"icon\":\"https:\\\/\\\/map-mobile-resource.cdn.bcebos.com\\\/icon\\\/rec\\\/search\\\/default\\\/jiayou.png\",\"text\":\"\u52a0\u6cb9\u7ad9\",\"type\":1}]","route_flag":0,"show_tag":[],"status":1,"std_tag":"\u65c5\u6e38\u666f\u70b9;\u516c\u56ed","std_tag_id":"1502","storage_src":"api","tag":"\u65c5\u6e38<font color=\"#c60a00\">\u666f\u70b9<\/font> \u516c\u56ed","title_color_shows":[],"top1_reinforce":0,"ty":0,"uid":"579efd5b8035faa5593ac8d2","view_type":0,"x":1268964819,"y":257806710},{"acc_flag":0,"addr":"\u6df1\u5733\u5e02\u9f99\u534e\u533a\u817e\u9f99\u8def\u9f99\u5858\u65b0\u6751\u897f\u5317\u4fa7","addr_hot_percent":0,"address_color_shows":[{"end":12,"name":"\u6df1\u5733\u5e02\u9f99\u534e\u533a","start":0}],"address_norm":"[\u5e7f\u4e1c\u7701(440000)|PROV|0|][\u6df1\u5733\u5e02(440300)|CITY|1|][\u9f99\u534e\u533a(440309)|AREA|1|][\u817e\u9f99\u8def()|ROAD|1|]\u9f99\u5858\u65b0\u6751\u897f\u5317\u4fa7","admin_info":{"area_id":440309,"area_name":"\u9f99\u534e\u533a","city_id":440300,"city_name":"\u6df1\u5733\u5e02","province_id":440000,"province_name":"\u5e7f\u4e1c\u7701","town_id":440309003,"town_name":"\u6c11\u6cbb\u8857\u9053"},"aoi":"\u6c11\u6cbb;\u4e0a\u5858;\u9f99\u534e","api_admin_info":{"area_code":3352,"area_name":"\u9f99\u534e\u533a","city_code":340,"city_name":"\u6df1\u5733\u5e02","prov_code":7,"prov_name":"\u5e7f\u4e1c\u7701"},"area":3352,"area_name":"\u6df1\u5733\u5e02\u9f99\u534e\u533a","biz_type":0,"brand_id":null,"catalogID":0,"city_id":340,"city_name":"\u6df1\u5733\u5e02","cla":[],"class_similar_score":0.47896924614906,"click_flag":0,"detail":1,"diPointX":1269276991,"diPointY":257207817,"di_tag":"\u65c5\u6e38\u666f\u70b9 \u516c\u56ed \u4e3b\u9898\u516c\u56ed","dis":-1,"dist2route":0,"dist2start":0,"ernie_score":0,"ext":{"detail_info":{"areaid":"3352","bubble_info":{"icon":{"dark_icon_url":null,"icon_url":null,"std_tag":"\u65c5\u6e38\u666f\u70b9;\u516c\u56ed"},"mark":null,"sub_title":null,"tag":null,"title":null},"content_sug":{"search_ext_data":{"full_text":[]},"sug_ext_data":{"full_text":[],"sub_link_info":[]}},"default_image":"https:\/\/map-mobile-resource.cdn.bcebos.com\/icon\/rec\/search\/default\/huanzigongyuan.png","from_pds":"1","image":"https:\/\/map-mobile-resource.cdn.bcebos.com\/icon\/rec\/search\/default\/huanzigongyuan.png","is_default_image":"1","mbc":{"markv":"1"},"name":"\u6c11\u6cbb\u8857\u9053\u6d88\u9632\u5b89\u5168\u4e3b\u9898\u516c\u56ed","phone":"","poi_address":"\u6df1\u5733\u5e02\u9f99\u534e\u533a\u817e\u9f99\u8def\u9f99\u5858\u65b0\u6751\u897f\u5317\u4fa7","point":{"x":12692769.91,"y":2572078.17},"short_desc":"","std_tag":"\u65c5\u6e38\u666f\u70b9;\u516c\u56ed","tag":"\u65c5\u6e38\u666f\u70b9 \u516c\u56ed \u4e3b\u9898\u516c\u56ed","travel_info":{"navi_parking_relation":{"rec_parkings":[{"distance":195,"is_children_parking":0,"is_confi_parking":0,"name":"AT MALL\u4e0a\u5858\u835f-\u5730\u4e0b\u505c\u8f66\u573a","std_tag":"\u4ea4\u901a\u8bbe\u65bd;\u505c\u8f66\u573a","uid":"ffba8567041a34c275e5b63e"},{"distance":449,"is_children_parking":0,"is_confi_parking":0,"name":"\u7b80\u4e0a\u6751-\u505c\u8f66\u573a","std_tag":"\u4ea4\u901a\u8bbe\u65bd;\u505c\u8f66\u573a","uid":"a83ec1c6641514e7c9fa5ffa"}],"transfer":1,"update_time":1700498232.9532}},"vs_content":{"invisible":{"bigdata":{"showtag":"[[\"\\u516c\\u56ed\"], [\"\"], \"\", 0, \"\"]"}}}},"src_name":"scope"},"ext_display":null,"ext_type":4,"f_flag":8,"father_son":0,"gbrank_score":-8.9595276964863,"geo":"1|12692769.91,2572078.17;12692769.91,2572078.17|12692769.91,2572078.17;","geo_type":0,"history_address":"\u6df1\u5733\u5e02","hit_tag_press":0,"is_nearnest_nat":0,"is_top_nat":0,"name":"\u6c11\u6cbb\u8857\u9053\u6d88\u9632\u5b89\u5168\u4e3b\u9898\u516c\u56ed","navi_update_time":1700498232,"navi_x":"0","navi_y":"0","new_catalog_id":"0c0000","poiType":0,"poi_click_num":0,"poi_profile":0,"primary_uid":"3716564331021797330","prio_flag":32,"qu_brandid":0,"query_guide":"[{\"icon\":\"https:\\\/\\\/map-mobile-resource.cdn.bcebos.com\\\/icon\\\/service\\\/search\\\/default\\\/meishi5.png\",\"text\":\"\u7f8e\u98df\",\"type\":1},{\"icon\":\"https:\\\/\\\/map-mobile-resource.cdn.bcebos.com\\\/icon\\\/rec\\\/search\\\/default\\\/jiudian.png\",\"text\":\"\u9152\u5e97\",\"type\":1},{\"icon\":\"https:\\\/\\\/map-mobile-resource.cdn.bcebos.com\\\/icon\\\/rec\\\/search\\\/default\\\/jingdian.png\",\"text\":\"\u666f\u70b9\",\"type\":1},{\"icon\":\"https:\\\/\\\/map-mobile-resource.cdn.bcebos.com\\\/icon\\\/rec\\\/search\\\/default\\\/tingchechang.png\",\"text\":\"\u505c\u8f66\u573a\",\"type\":1},{\"icon\":\"https:\\\/\\\/map-mobile-resource.cdn.bcebos.com\\\/icon\\\/rec\\\/search\\\/default\\\/xiuxianyule.png\",\"text\":\"\u4f11\u95f2\u5a31\u4e50\",\"type\":1},{\"icon\":\"https:\\\/\\\/map-mobile-resource.cdn.bcebos.com\\\/icon\\\/service\\\/search\\\/default\\\/gouwu5.png\",\"text\":\"\u8d2d\u7269\",\"type\":1},{\"icon\":\"https:\\\/\\\/map-mobile-resource.cdn.bcebos.com\\\/icon\\\/rec\\\/search\\\/default\\\/jiayou.png\",\"text\":\"\u52a0\u6cb9\u7ad9\",\"type\":1}]","route_flag":0,"show_tag":[],"status":1,"std_tag":"\u65c5\u6e38\u666f\u70b9;\u516c\u56ed","std_tag_id":"1502","storage_src":"api","tag":"\u65c5\u6e38<font color=\"#c60a00\">\u666f\u70b9<\/font> \u516c\u56ed \u4e3b\u9898\u516c\u56ed","title_color_shows":[],"top1_reinforce":0,"ty":0,"uid":"6b10e17d78e91950d23ce36d","view_type":0,"x":1269276991,"y":257207817},{"acc_flag":0,"addr":"\u6df1\u5733\u5e02\u9f99\u534e\u533a\u6a1f\u9601\u8def\u7ae0\u9601\u65b0\u6751\u897f\u5317\u4fa7\u7ea6110\u7c73","addr_hot_percent":0,"address_color_shows":[{"end":12,"name":"\u6df1\u5733\u5e02\u9f99\u534e\u533a","start":0}],"address_norm":"[\u5e7f\u4e1c\u7701(440000)|PROV|0|][\u6df1\u5733\u5e02(440300)|CITY|1|][\u9f99\u534e\u533a(440309)|AREA|1|][\u6a1f\u9601\u8def()|ROAD|1|]\u7ae0\u9601\u65b0\u6751\u897f\u5317\u4fa7\u7ea6110\u7c73","admin_info":{"area_id":440309,"area_name":"\u9f99\u534e\u533a","city_id":440300,"city_name":"\u6df1\u5733\u5e02","province_id":440000,"province_name":"\u5e7f\u4e1c\u7701","town_id":440309006,"town_name":"\u798f\u57ce\u8857\u9053"},"api_admin_info":{"area_code":3352,"area_name":"\u9f99\u534e\u533a","city_code":340,"city_name":"\u6df1\u5733\u5e02","prov_code":7,"prov_name":"\u5e7f\u4e1c\u7701"},"area":3352,"area_name":"\u6df1\u5733\u5e02\u9f99\u534e\u533a","biz_type":0,"brand_id":null,"catalogID":0,"city_id":340,"city_name":"\u6df1\u5733\u5e02","cla":[],"class_similar_score":0.52395248413086,"click_flag":0,"detail":1,"diPointX":1269312112,"diPointY":258558563,"di_tag":"\u540d\u80dc\u53e4\u8ff9 \u65c5\u6e38\u666f\u70b9","dis":-1,"dist2route":0,"dist2start":0,"ernie_score":0,"ext":{"detail_info":{"areaid":"3352","bubble_info":{"icon":{"dark_icon_url":null,"icon_url":null,"std_tag":"\u65c5\u6e38\u666f\u70b9;\u6587\u7269\u53e4\u8ff9"},"mark":null,"sub_title":null,"tag":null,"title":null},"comments":[],"content_sug":{"search_ext_data":{"full_text":[]},"sug_ext_data":{"full_text":[],"sub_link_info":[]}},"default_image":"https:\/\/map-mobile-resource.cdn.bcebos.com\/icon\/rec\/search\/default\/huanziwenwuguji.png","description_flag":"","entrance_price":"","free":2,"from_pds":"1","guide":0,"image":"https:\/\/map-mobile-resource.cdn.bcebos.com\/icon\/rec\/search\/default\/huanziwenwuguji.png","is_default_image":"1","link":[],"list_min_price":0,"list_min_price_save":0,"mbc":{"markv":"1"},"name":"\u6da6\u5fb7\u516c\u7960","overall_rating":"","phone":"","poi_address":"\u6df1\u5733\u5e02\u9f99\u534e\u533a\u6a1f\u9601\u8def\u7ae0\u9601\u65b0\u6751\u897f\u5317\u4fa7\u7ea6110\u7c73","poi_tags":{"attr_tag":[{"from":"time_renqun_new","invisible":1,"name":"\u9002\u5408\u5e74\u8f7b\u4eba","rate":1,"rec_num":1,"rec_reason":"\u9002\u5408\u5e74\u8f7b\u4eba\u805a\u96c6\u7684\u6c1b\u56f4\u89e3\u538b\u5b9d\u5730","type":2}],"transfer_update":1},"point":{"x":12693121.12,"y":2585585.63},"price":false,"refer_price":"","scope_grade":"","shop_hours_flag":"","short_desc":"","std_tag":"\u65c5\u6e38\u666f\u70b9;\u6587\u7269\u53e4\u8ff9","tag":"\u666f\u533a,","travel_info":{"navi_parking_relation":{"rec_parkings":[{"distance":327,"is_children_parking":0,"is_confi_parking":0,"name":"\u7ae0\u9601\u5ba2\u5bb6\u98df\u5e9c(\u6a1f\u9601\u8def\u5e97)-\u505c\u8f66\u573a","std_tag":"\u4ea4\u901a\u8bbe\u65bd;\u505c\u8f66\u573a","uid":"105443acf08ff4abfb0cadb2"},{"distance":441,"is_children_parking":0,"is_confi_parking":0,"name":"\u7ae0\u9601\u4f1f\u9686-\u505c\u8f66\u573a","std_tag":"\u4ea4\u901a\u8bbe\u65bd;\u505c\u8f66\u573a","uid":"51245e7bddc051c33686f420"}],"transfer":1,"update_time":1695381787.1255}},"vs_content":{"invisible":{"bigdata":{"dyn_style":"{\"dish\": [[\"\\u63a8\\u8350\\u83dc:{name}\", \"\"], [\"24\", \"24\"], \"310\", 2, \"\"]}","idx_type":"{\"1\": \"\\u83dc\\u54c1\", \"2\": \"\\u670d\\u52a1\\u5185\\u5bb9\", \"3\": \"\\u5546\\u54c1\", \"4\": \"\\u5b50\\u7c7b\\u578b\"}","showtag":"[[\"\\u540d\\u80dc\\u53e4\\u8ff9\"], [\"\"], \"\", 0, \"\"]","style":"{\"24\": \"#F76454\", \"310\": \"#FEEFED\"}"}}}},"src_name":"scope"},"ext_display":null,"ext_type":4,"f_flag":8,"father_son":0,"gbrank_score":-8.9607296778958,"geo":"1|12693121.12,2585585.63;12693121.12,2585585.63|12693121.12,2585585.63;","geo_type":0,"history_address":"\u6df1\u5733\u5e02","hit_tag_press":0,"is_nearnest_nat":0,"is_top_nat":0,"name":"\u6da6\u5fb7\u516c\u7960","navi_update_time":1695381787,"navi_x":"0","navi_y":"0","new_catalog_id":"0c0000","poiType":0,"poi_click_num":0,"poi_profile":0,"primary_uid":"16322965433195814761","prio_flag":32,"qu_brandid":0,"query_guide":"[{\"icon\":\"https:\\\/\\\/map-mobile-resource.cdn.bcebos.com\\\/icon\\\/service\\\/search\\\/default\\\/meishi5.png\",\"text\":\"\u7f8e\u98df\",\"type\":1},{\"icon\":\"https:\\\/\\\/map-mobile-resource.cdn.bcebos.com\\\/icon\\\/rec\\\/search\\\/default\\\/jiudian.png\",\"text\":\"\u9152\u5e97\",\"type\":1},{\"icon\":\"https:\\\/\\\/map-mobile-resource.cdn.bcebos.com\\\/icon\\\/rec\\\/search\\\/default\\\/jingdian.png\",\"text\":\"\u666f\u70b9\",\"type\":1},{\"icon\":\"https:\\\/\\\/map-mobile-resource.cdn.bcebos.com\\\/icon\\\/rec\\\/search\\\/default\\\/tingchechang.png\",\"text\":\"\u505c\u8f66\u573a\",\"type\":1},{\"icon\":\"https:\\\/\\\/map-mobile-resource.cdn.bcebos.com\\\/icon\\\/rec\\\/search\\\/default\\\/xiuxianyule.png\",\"text\":\"\u4f11\u95f2\u5a31\u4e50\",\"type\":1},{\"icon\":\"https:\\\/\\\/map-mobile-resource.cdn.bcebos.com\\\/icon\\\/service\\\/search\\\/default\\\/gouwu5.png\",\"text\":\"\u8d2d\u7269\",\"type\":1},{\"icon\":\"https:\\\/\\\/map-mobile-resource.cdn.bcebos.com\\\/icon\\\/rec\\\/search\\\/default\\\/jiayou.png\",\"text\":\"\u52a0\u6cb9\u7ad9\",\"type\":1}]","route_flag":0,"show_tag":[],"status":1,"std_tag":"\u65c5\u6e38\u666f\u70b9;\u6587\u7269\u53e4\u8ff9","std_tag_id":"1509","storage_src":"api","tag":"\u540d\u80dc\u53e4\u8ff9 \u65c5\u6e38<font color=\"#c60a00\">\u666f\u70b9<\/font>","title_color_shows":[],"top1_reinforce":0,"ty":0,"uid":"099f8c2b7e0d712dede4a5ae","view_type":0,"x":1269312112,"y":258558563},{"acc_flag":0,"addr":"\u5927\u6d6a\u4e49\u4e4c\u5c0f\u5546\u54c1\u57ce3\u697c","area":2617,"area_name":"\u6df1\u5733\u5e02\u5b9d\u5b89\u533a","biz_type":0,"brand_id":null,"catalogID":0,"cla":[],"click_flag":0,"detail":1,"diPointX":1269157092,"diPointY":257715255,"di_tag":"","dis":-1,"dist2route":0,"dist2start":0,"ext":{"detail_info":{"areaid":"2617","from_pds":"1","name":"BIRD","phone":"","poi_address":"\u5927\u6d6a\u4e49\u4e4c\u5c0f\u5546\u54c1\u57ce3\u697c","point":{"x":12691570.92,"y":2575513}},"gray_line":{"mohushangxiaxian":{"color":"#999999","text":"\u8be5\u5546\u6237\u8425\u4e1a\u72b6\u6001\u53ef\u80fd\u6709\u53d8\u5316\uff0c\u8bf7\u786e\u8ba4\u540e\u524d\u5f80"}},"poi_status":{"mohushangxiaxian":{"color":"#3385ff","text":""}}},"ext_display":{"display_info":{"catalog_fields":null,"impression_tag":{"hotel":"","life":""},"redu":"19","source_map":[],"src_name":"display_info","uids":["1934035204523023596:redu","1934035204523023596"]}},"ext_type":4,"f_flag":1,"father_son":0,"geo":"1|12691570.92,2577152.550;12691570.92,2577152.550|12691570.92,2577152.550;","geo_type":2,"indoor_pano":"","ismodified":0,"name":"BIRD","navi_update_time":1518625902,"navi_x":"12691570.92","navi_y":"2577152.55","pano":1,"poiType":0,"poi_click_num":0,"poi_profile":0,"primary_uid":"1934035204523023596","prio_flag":33,"route_flag":0,"show_tag":[],"status":16,"std_tag":"\u8d2d\u7269;\u5546\u94fa","std_tag_id":"1207","storage_src":"api","street_id":"3604f065de0a879449fc8d42","tag":"","ty":2,"uid":"3604f065de0a879449fc8d42","view_type":0,"x":1269157092,"y":257715255}],"current_city":{"code":340,"geo":"1|12697919.69,2560977.31;12697919.69,2560977.31|12697919.69,2560977.31;","level":12,"name":"\u6df1\u5733\u5e02","sup":1,"sup_bus":1,"sup_business_area":1,"sup_lukuang":1,"sup_subway":1,"type":2,"up_province_name":"\u5e7f\u4e1c\u7701"},"hot_city":["\u5317\u4eac\u5e02|131","\u4e0a\u6d77\u5e02|289","\u5e7f\u5dde\u5e02|257","\u6df1\u5733\u5e02|340","\u6210\u90fd\u5e02|75","\u5929\u6d25\u5e02|332","\u5357\u4eac\u5e02|315","\u676d\u5dde\u5e02|179","\u6b66\u6c49\u5e02|218"],"result":{"ad_display_type":0,"aladdin_res_num":111,"aladin_query_type":0,"area_profile":1,"attribute_tags":[],"bd_search_enable":0,"broadcast_type":0,"business_bound":"","catalogID":0,"cmd_no":2,"count":10,"current_null":0,"data_security_filt_res":0,"db":0,"debug":0,"illegal":0,"jump_back":1,"loc_attr":0,"op_gel":1,"page_num":8,"pattern_sign":0,"pre_filter_info":[{"dup":1,"n":"\u89c2\u6f9c\u9644\u8fd1","overwrite_k":"fp_business_area","overwrite_k_exclusive":1,"v":"340_\u89c2\u6f9c"}],"profile_uid":"579efd5b8035faa5593ac8d2","qid":"711265810636777874","query_tags":[{"id":391,"name":"\u98ce\u666f\u533a","score":0.80634522438049}],"rec_query_flag":0,"requery":"","res_bound":"(12688313,2567411;12704327,2587956)","res_bound_acc":"(0,0;0,0)","res_l":13,"res_x":"12696320.780000","res_y":"2577683.730000","result_show":0,"return_query":"\u6df1\u5733\u5e02\u9f99\u534e\u533a\u666f\u70b9","rp_strategy":0,"spec_dispnum":0,"spothot":false,"sug_index":-1,"time":0,"total":115,"total_busline_num":0,"tp":0,"type":36,"wd":"\u6df1\u5733\u5e02\u9f99\u534e\u533a\u666f\u70b9","wd2":"","what":"\u666f\u70b9","where":"\u6df1\u5733\u5e02\u9f99\u534e\u533a","uii_type":"china_main","region":"0","uii_qt":"poi","login_debug":1,"lbs_forward":{"param":[{"cloud_control_browser":"","cloud_control_cf_tag":"","cloud_control_params":"","d_brand_id":"0","d_query_attr_type":"2","d_tag_info_list":"\u65c5\u6e38\u666f\u70b9","divide_bound_areaid":340,"divide_loc_areaid":0,"divide_res_areaid":340,"divide_type":0,"is_viewcity_has_result":true,"low_freq_gel_type":34,"query_show_click_flag":0,"sample_experiment":[],"semantic_type":130,"view_city":340}]},"auth":"YPIS0xEeYE46HwTxzdDWA=GDXL6K9QI5uxNVRLRVNRNtE@@KNTXRKKCEKEBwyS8v7uvkGcuVtvvhguVtvyheuxtwD42v7uvCQMuVtvIPcuxtw8wkv7uvZgMuVtv@vcuVtvc3CuVtvcPPuVtveGvuHRztxgjLwWvvh3CuVtvhgMuzVVtvrMhuxVTBt5ooioGdFcvY1SGpuzVtegvcguxNVRLNTTHE"},"damoce":null}